flytekitplugins_great_expectations-1.16.12-py3.14-nspkg.pth
flytekitplugins/great_expectations/__init__.py
flytekitplugins/great_expectations/schema.py
flytekitplugins/great_expectations/task.py
flytekitplugins_great_expectations-1.16.12.dist-info/METADATA
flytekitplugins_great_expectations-1.16.12.dist-info/WHEEL
flytekitplugins_great_expectations-1.16.12.dist-info/namespace_packages.txt
flytekitplugins_great_expectations-1.16.12.dist-info/top_level.txt
flytekitplugins_great_expectations-1.16.12.dist-info/RECORD
