Metadata-Version: 2.4
Name: flytekitplugins-great_expectations
Version: 1.16.12
Summary: Great Expectations Plugin for Flytekit
Author: flyteorg
Author-email: admin@flyte.org
License: apache2
Classifier: Intended Audience :: Science/Research
Classifier: Intended Audience :: Developers
Classifier: License :: OSI Approved :: Apache Software License
Classifier: Programming Language :: Python :: 3.9
Classifier: Programming Language :: Python :: 3.10
Classifier: Topic :: Scientific/Engineering
Classifier: Topic :: Scientific/Engineering :: Artificial Intelligence
Classifier: Topic :: Software Development
Classifier: Topic :: Software Development :: Libraries
Classifier: Topic :: Software Development :: Libraries :: Python Modules
Requires-Python: >=3.9
Requires-Dist: flytekit>=1.5.0
Requires-Dist: great-expectations<1.0.0,>=0.13.30
Requires-Dist: sqlalchemy>=1.4.23
Requires-Dist: pyspark==3.3.2
Requires-Dist: s3fs<2023.6.0
Dynamic: author
Dynamic: author-email
Dynamic: classifier
Dynamic: license
Dynamic: requires-dist
Dynamic: requires-python
Dynamic: summary
